{
  "project_info": {
    "project_number": "338791306953",
    "firebase_url": "https://faceit-stats-f8fde.firebaseio.com",
    "project_id": "faceit-stats-f8fde",
    "storage_bucket": "faceit-stats-f8fde.appspot.com"
  },
  "client": [
    {
      "client_info": {
        "mobilesdk_app_id": "1:338791306953:android:c8867a97b16763a6b1df18",
        "android_client_info": {
          "package_name": "com.potatocouch.faceit_stats"
        }
      },
      "oauth_client": [
        {
          "client_id": "338791306953-ahshd6d77mtfdkass473n3r038dj0n7o.apps.googleusercontent.com",
          "client_type": 1,
          "android_info": {
            "package_name": "com.potatocouch.faceit_stats",
            "certificate_hash": "051cfb0b48b4e789d40f40f2f6a7f9fba0047eda"
          }
        },
        {
          "client_id": "338791306953-a971mr73op29ivrn6vqiruhsh1eqf7ve.apps.googleusercontent.com",
          "client_type": 3
        }
      ],
      "api_key": [
        {
          "current_key": "AIzaSyCWj-m0ria0g6I9jY1soNLzn9FoJVv7cJM"
        }
      ],
      "services": {
        "appinvite_service": {
          "other_platform_oauth_client": [
            {
              "client_id": "338791306953-a971mr73op29ivrn6vqiruhsh1eqf7ve.apps.googleusercontent.com",
              "client_type": 3
            }
          ]
        }
      },
      "admob_app_id": "ca-app-pub-5167276366193403~3958343265"
    }
  ],
  "configuration_version": "1"
}